{
  "name": "Category",
  "fields": [
    {
      "fieldName": "name",
      "fieldType": "String",
      "fieldValidateRules": [
        "required"
      ]
    },
    {
      "fieldName": "description",
      "fieldType": "String",
      "fieldValidateRules": [
        "required"
      ]
    },
    {
      "fieldName": "status",
      "fieldType": "CategoryStatus",
      "fieldValues": "ENABLED,DISABLED",
      "fieldValidateRules": [
        "required"
      ]
    }
  ],
  "relationships": [
    {
      "relationshipType": "one-to-one",
      "otherEntityName": "image",
      "otherEntityRelationshipName": "category",
      "relationshipName": "image",
      "otherEntityField": "id",
      "ownerSide": true
    },
    {
      "relationshipType": "one-to-many",
      "otherEntityName": "proyect",
      "otherEntityRelationshipName": "category",
      "relationshipName": "proyect"
    }
  ],
  "changelogDate": "20201103004127",
  "entityTableName": "category",
  "dto": "no",
  "pagination": "no",
  "service": "no",
  "jpaMetamodelFiltering": false,
  "fluentMethods": true,
  "readOnly": false,
  "embedded": false,
  "clientRootFolder": "",
  "applications": "*"
}
